linearalgcalc/__init__.py
linearalgcalc/myfunctions.py
linearalgcalc-0.1.1.dist-info/LICENSE.txt
linearalgcalc-0.1.1.dist-info/METADATA
linearalgcalc-0.1.1.dist-info/WHEEL
linearalgcalc-0.1.1.dist-info/top_level.txt
linearalgcalc-0.1.1.dist-info/RECORD
