Metadata-Version: 2.1
Name: linearalgcalc
Version: 0.1.1
Summary: A library for linear algebra calculations
Home-page: UNKNOWN
Author: Jinha Kim
License: MIT
Platform: UNKNOWN
